Workbook

Sheet Budget
B1: Budget de diffusion de l'offre – Avocat(e) salarié(e)
B2: Victimes & Préjudices Avocats · estimation du budget mensuel par plateforme et par scénario. Cellules jaunes = saisie ; cellules grises = calcul automatique.
B4: PARAMÈTRES | F4: BUDGET DU SCÉNARIO RETENU
B5: Début de la diffusion | C5: 46296 | F5: ="Scénario "&$C$9&" · campagne de "&$C$6&" mois" -> Scénario Équilibré · campagne de 2 mois | K5: HT | L5: TTC
B6: Durée de la campagne (mois) | C6: 2 | F6: Budget mensuel moyen à allouer | K6: =IF($C$7="HT",CHOOSE($C$10,$Q$25,$S$25,$U$25)/$C$6,CHOOSE($C$10,$Q$25,$S$25,$U$25)/$C$6/(1+$C$8)) -> 595 | L6: =IF($C$7="HT",CHOOSE($C$10,$Q$25,$S$25,$U$25)/$C$6*(1+$C$8),CHOOSE($C$10,$Q$25,$S$25,$U$25)/$C$6) -> 714
B7: Tarifs saisis en | C7: HT | F7: Décaissement du 1er mois (forfait payé d'avance) | K7: =IF($C$7="HT",CHOOSE($C$10,$P$25,$R$25,$T$25),CHOOSE($C$10,$P$25,$R$25,$T$25)/(1+$C$8)) -> 740 | L7: =IF($C$7="HT",CHOOSE($C$10,$P$25,$R$25,$T$25)*(1+$C$8),CHOOSE($C$10,$P$25,$R$25,$T$25)) -> 888
B8: Taux de TVA | C8: 0.2 | F8: Budget total de la campagne | K8: =IF($C$7="HT",CHOOSE($C$10,$Q$25,$S$25,$U$25),CHOOSE($C$10,$Q$25,$S$25,$U$25)/(1+$C$8)) -> 1190 | L8: =IF($C$7="HT",CHOOSE($C$10,$Q$25,$S$25,$U$25)*(1+$C$8),CHOOSE($C$10,$Q$25,$S$25,$U$25)) -> 1428
B9: Scénario retenu | C9: Équilibré | F9: Plateformes utilisées (dont payantes) | K9: =COUNTIF($O$13:$O$24,">0")&" ("&CHOOSE($C$10,$G$25,$I$25,$K$25)&")" -> 10 (4)
B10: Numéro du scénario retenu | C10: =MATCH($C$9,$B$29:$B$31,0) -> 2
B11: PLATEFORMES ET TARIFS | G11: ESSENTIEL | I11: ÉQUILIBRÉ | K11: INTENSIF | M11: COMMENTAIRES | O11: DÉTAIL DES CALCULS (ne pas modifier)
B12: Plateforme | C12: Formule | D12: Tarif (€) | E12: Facturation | F12: Durée du forfait (mois) | G12: Qté / mois | H12: Coût / mois | I12: Qté / mois | J12: Coût / mois | K12: Qté / mois | L12: Coût / mois | O12: Qté du scénario retenu | P12: 1er mois Essentiel | Q12: Campagne Essentiel | R12: 1er mois Équilibré | S12: Campagne Équilibré | T12: 1er mois Intensif | U12: Campagne Intensif
B13: Village de la Justice | C13: Annonce Premium | D13: 290 | E13: Forfait | F13: 2 | G13: 1 | H13: =IF(OR($G13="",N($G13)=0,$E13="",$E13="Gratuit"),0,IF($E13="Forfait",N($D13)/MAX(1,N($F13)),N($D13)*$G13)) -> 145 | I13: 1 | J13: =IF(OR($I13="",N($I13)=0,$E13="",$E13="Gratuit"),0,IF($E13="Forfait",N($D13)/MAX(1,N($F13)),N($D13)*$I13)) -> 145 | K13: 1 | L13: =IF(OR($K13="",N($K13)=0,$E13="",$E13="Gratuit"),0,IF($E13="Forfait",N($D13)/MAX(1,N($F13)),N($D13)*$K13)) -> 145 | M13: 290 € pour 2 mois, payés à la publication. Site de référence des professions du droit. | O13: =CHOOSE($C$10,G13,I13,K13) -> 1 | P13: =IF(OR($G13="",N($G13)=0,$E13="",$E13="Gratuit"),0,IF($E13="Forfait",N($D13),N($D13)*$G13)) -> 290 | Q13: =IF(OR($G13="",N($G13)=0,$E13="",$E13="Gratuit"),0,IF($E13="Forfait",N($D13)*ROUNDUP($C$6/MAX(1,N($F13)),0),N($D13)*$G13*$C$6)) -> 290 | R13: =IF(OR($I13="",N($I13)=0,$E13="",$E13="Gratuit"),0,IF($E13="Forfait",N($D13),N($D13)*$I13)) -> 290 | S13: =IF(OR($I13="",N($I13)=0,$E13="",$E13="Gratuit"),0,IF($E13="Forfait",N($D13)*ROUNDUP($C$6/MAX(1,N($F13)),0),N($D13)*$I13*$C$6)) -> 290 | T13: =IF(OR($K13="",N($K13)=0,$E13="",$E13="Gratuit"),0,IF($E13="Forfait",N($D13),N($D13)*$K13)) -> 290 | U13: =IF(OR($K13="",N($K13)=0,$E13="",$E13="Gratuit"),0,IF($E13="Forfait",N($D13)*ROUNDUP($C$6/MAX(1,N($F13)),0),N($D13)*$K13*$C$6)) -> 290
B14: RecrutAvocat | C14: Annonce | D14: 0 | E14: Gratuit | G14: 1 | H14: =IF(OR($G14="",N($G14)=0,$E14="",$E14="Gratuit"),0,IF($E14="Forfait",N($D14)/MAX(1,N($F14)),N($D14)*$G14)) -> 0 | I14: 1 | J14: =IF(OR($I14="",N($I14)=0,$E14="",$E14="Gratuit"),0,IF($E14="Forfait",N($D14)/MAX(1,N($F14)),N($D14)*$I14)) -> 0 | K14: 1 | L14: =IF(OR($K14="",N($K14)=0,$E14="",$E14="Gratuit"),0,IF($E14="Forfait",N($D14)/MAX(1,N($F14)),N($D14)*$K14)) -> 0 | M14: Site spécialisé dans le recrutement d'avocats. | O14: =CHOOSE($C$10,G14,I14,K14) -> 1 | P14: =IF(OR($G14="",N($G14)=0,$E14="",$E14="Gratuit"),0,IF($E14="Forfait",N($D14),N($D14)*$G14)) -> 0 | Q14: =IF(OR($G14="",N($G14)=0,$E14="",$E14="Gratuit"),0,IF($E14="Forfait",N($D14)*ROUNDUP($C$6/MAX(1,N($F14)),0),N($D14)*$G14*$C$6)) -> 0 | R14: =IF(OR($I14="",N($I14)=0,$E14="",$E14="Gratuit"),0,IF($E14="Forfait",N($D14),N($D14)*$I14)) -> 0 | S14: =IF(OR($I14="",N($I14)=0,$E14="",$E14="Gratuit"),0,IF($E14="Forfait",N($D14)*ROUNDUP($C$6/MAX(1,N($F14)),0),N($D14)*$I14*$C$6)) -> 0 | T14: =IF(OR($K14="",N($K14)=0,$E14="",$E14="Gratuit"),0,IF($E14="Forfait",N($D14),N($D14)*$K14)) -> 0 | U14: =IF(OR($K14="",N($K14)=0,$E14="",$E14="Gratuit"),0,IF($E14="Forfait",N($D14)*ROUNDUP($C$6/MAX(1,N($F14)),0),N($D14)*$K14*$C$6)) -> 0
B15: LinkedIn | C15: Offre d'emploi | D15: 0 | E15: Gratuit | G15: 1 | H15: =IF(OR($G15="",N($G15)=0,$E15="",$E15="Gratuit"),0,IF($E15="Forfait",N($D15)/MAX(1,N($F15)),N($D15)*$G15)) -> 0 | I15: 1 | J15: =IF(OR($I15="",N($I15)=0,$E15="",$E15="Gratuit"),0,IF($E15="Forfait",N($D15)/MAX(1,N($F15)),N($D15)*$I15)) -> 0 | K15: 1 | L15: =IF(OR($K15="",N($K15)=0,$E15="",$E15="Gratuit"),0,IF($E15="Forfait",N($D15)/MAX(1,N($F15)),N($D15)*$K15)) -> 0 | M15: Publication de l'offre gratuite. | O15: =CHOOSE($C$10,G15,I15,K15) -> 1 | P15: =IF(OR($G15="",N($G15)=0,$E15="",$E15="Gratuit"),0,IF($E15="Forfait",N($D15),N($D15)*$G15)) -> 0 | Q15: =IF(OR($G15="",N($G15)=0,$E15="",$E15="Gratuit"),0,IF($E15="Forfait",N($D15)*ROUNDUP($C$6/MAX(1,N($F15)),0),N($D15)*$G15*$C$6)) -> 0 | R15: =IF(OR($I15="",N($I15)=0,$E15="",$E15="Gratuit"),0,IF($E15="Forfait",N($D15),N($D15)*$I15)) -> 0 | S15: =IF(OR($I15="",N($I15)=0,$E15="",$E15="Gratuit"),0,IF($E15="Forfait",N($D15)*ROUNDUP($C$6/MAX(1,N($F15)),0),N($D15)*$I15*$C$6)) -> 0 | T15: =IF(OR($K15="",N($K15)=0,$E15="",$E15="Gratuit"),0,IF($E15="Forfait",N($D15),N($D15)*$K15)) -> 0 | U15: =IF(OR($K15="",N($K15)=0,$E15="",$E15="Gratuit"),0,IF($E15="Forfait",N($D15)*ROUNDUP($C$6/MAX(1,N($F15)),0),N($D15)*$K15*$C$6)) -> 0
B16: LinkedIn | C16: Boost de l'offre | D16: 10 | E16: Par jour | G16: 0 | H16: =IF(OR($G16="",N($G16)=0,$E16="",$E16="Gratuit"),0,IF($E16="Forfait",N($D16)/MAX(1,N($F16)),N($D16)*$G16)) -> 0 | I16: 15 | J16: =IF(OR($I16="",N($I16)=0,$E16="",$E16="Gratuit"),0,IF($E16="Forfait",N($D16)/MAX(1,N($F16)),N($D16)*$I16)) -> 150 | K16: 30 | L16: =IF(OR($K16="",N($K16)=0,$E16="",$E16="Gratuit"),0,IF($E16="Forfait",N($D16)/MAX(1,N($F16)),N($D16)*$K16)) -> 300 | M16: Budget journalier maximal : la dépense réelle peut être inférieure. | O16: =CHOOSE($C$10,G16,I16,K16) -> 15 | P16: =IF(OR($G16="",N($G16)=0,$E16="",$E16="Gratuit"),0,IF($E16="Forfait",N($D16),N($D16)*$G16)) -> 0 | Q16: =IF(OR($G16="",N($G16)=0,$E16="",$E16="Gratuit"),0,IF($E16="Forfait",N($D16)*ROUNDUP($C$6/MAX(1,N($F16)),0),N($D16)*$G16*$C$6)) -> 0 | R16: =IF(OR($I16="",N($I16)=0,$E16="",$E16="Gratuit"),0,IF($E16="Forfait",N($D16),N($D16)*$I16)) -> 150 | S16: =IF(OR($I16="",N($I16)=0,$E16="",$E16="Gratuit"),0,IF($E16="Forfait",N($D16)*ROUNDUP($C$6/MAX(1,N($F16)),0),N($D16)*$I16*$C$6)) -> 300 | T16: =IF(OR($K16="",N($K16)=0,$E16="",$E16="Gratuit"),0,IF($E16="Forfait",N($D16),N($D16)*$K16)) -> 300 | U16: =IF(OR($K16="",N($K16)=0,$E16="",$E16="Gratuit"),0,IF($E16="Forfait",N($D16)*ROUNDUP($C$6/MAX(1,N($F16)),0),N($D16)*$K16*$C$6)) -> 600
B17: Indeed | C17: Annonce sponsorisée | D17: 100 | E17: Par semaine | G17: 0 | H17: =IF(OR($G17="",N($G17)=0,$E17="",$E17="Gratuit"),0,IF($E17="Forfait",N($D17)/MAX(1,N($F17)),N($D17)*$G17)) -> 0 | I17: 2 | J17: =IF(OR($I17="",N($I17)=0,$E17="",$E17="Gratuit"),0,IF($E17="Forfait",N($D17)/MAX(1,N($F17)),N($D17)*$I17)) -> 200 | K17: 4 | L17: =IF(OR($K17="",N($K17)=0,$E17="",$E17="Gratuit"),0,IF($E17="Forfait",N($D17)/MAX(1,N($F17)),N($D17)*$K17)) -> 400 | M17: Facturé à la semaine sponsorisée. | O17: =CHOOSE($C$10,G17,I17,K17) -> 2 | P17: =IF(OR($G17="",N($G17)=0,$E17="",$E17="Gratuit"),0,IF($E17="Forfait",N($D17),N($D17)*$G17)) -> 0 | Q17: =IF(OR($G17="",N($G17)=0,$E17="",$E17="Gratuit"),0,IF($E17="Forfait",N($D17)*ROUNDUP($C$6/MAX(1,N($F17)),0),N($D17)*$G17*$C$6)) -> 0 | R17: =IF(OR($I17="",N($I17)=0,$E17="",$E17="Gratuit"),0,IF($E17="Forfait",N($D17),N($D17)*$I17)) -> 200 | S17: =IF(OR($I17="",N($I17)=0,$E17="",$E17="Gratuit"),0,IF($E17="Forfait",N($D17)*ROUNDUP($C$6/MAX(1,N($F17)),0),N($D17)*$I17*$C$6)) -> 400 | T17: =IF(OR($K17="",N($K17)=0,$E17="",$E17="Gratuit"),0,IF($E17="Forfait",N($D17),N($D17)*$K17)) -> 400 | U17: =IF(OR($K17="",N($K17)=0,$E17="",$E17="Gratuit"),0,IF($E17="Forfait",N($D17)*ROUNDUP($C$6/MAX(1,N($F17)),0),N($D17)*$K17*$C$6)) -> 800
B18: France Travail | C18: Offre d'emploi | D18: 0 | E18: Gratuit | G18: 1 | H18: =IF(OR($G18="",N($G18)=0,$E18="",$E18="Gratuit"),0,IF($E18="Forfait",N($D18)/MAX(1,N($F18)),N($D18)*$G18)) -> 0 | I18: 1 | J18: =IF(OR($I18="",N($I18)=0,$E18="",$E18="Gratuit"),0,IF($E18="Forfait",N($D18)/MAX(1,N($F18)),N($D18)*$I18)) -> 0 | K18: 1 | L18: =IF(OR($K18="",N($K18)=0,$E18="",$E18="Gratuit"),0,IF($E18="Forfait",N($D18)/MAX(1,N($F18)),N($D18)*$K18)) -> 0 | O18: =CHOOSE($C$10,G18,I18,K18) -> 1 | P18: =IF(OR($G18="",N($G18)=0,$E18="",$E18="Gratuit"),0,IF($E18="Forfait",N($D18),N($D18)*$G18)) -> 0 | Q18: =IF(OR($G18="",N($G18)=0,$E18="",$E18="Gratuit"),0,IF($E18="Forfait",N($D18)*ROUNDUP($C$6/MAX(1,N($F18)),0),N($D18)*$G18*$C$6)) -> 0 | R18: =IF(OR($I18="",N($I18)=0,$E18="",$E18="Gratuit"),0,IF($E18="Forfait",N($D18),N($D18)*$I18)) -> 0 | S18: =IF(OR($I18="",N($I18)=0,$E18="",$E18="Gratuit"),0,IF($E18="Forfait",N($D18)*ROUNDUP($C$6/MAX(1,N($F18)),0),N($D18)*$I18*$C$6)) -> 0 | T18: =IF(OR($K18="",N($K18)=0,$E18="",$E18="Gratuit"),0,IF($E18="Forfait",N($D18),N($D18)*$K18)) -> 0 | U18: =IF(OR($K18="",N($K18)=0,$E18="",$E18="Gratuit"),0,IF($E18="Forfait",N($D18)*ROUNDUP($C$6/MAX(1,N($F18)),0),N($D18)*$K18*$C$6)) -> 0
B19: Apec | C19: Offre cadre | D19: 0 | E19: Gratuit | G19: 1 | H19: =IF(OR($G19="",N($G19)=0,$E19="",$E19="Gratuit"),0,IF($E19="Forfait",N($D19)/MAX(1,N($F19)),N($D19)*$G19)) -> 0 | I19: 1 | J19: =IF(OR($I19="",N($I19)=0,$E19="",$E19="Gratuit"),0,IF($E19="Forfait",N($D19)/MAX(1,N($F19)),N($D19)*$I19)) -> 0 | K19: 1 | L19: =IF(OR($K19="",N($K19)=0,$E19="",$E19="Gratuit"),0,IF($E19="Forfait",N($D19)/MAX(1,N($F19)),N($D19)*$K19)) -> 0 | M19: Poste cadre : cible les avocats salariés en poste ou en recherche. | O19: =CHOOSE($C$10,G19,I19,K19) -> 1 | P19: =IF(OR($G19="",N($G19)=0,$E19="",$E19="Gratuit"),0,IF($E19="Forfait",N($D19),N($D19)*$G19)) -> 0 | Q19: =IF(OR($G19="",N($G19)=0,$E19="",$E19="Gratuit"),0,IF($E19="Forfait",N($D19)*ROUNDUP($C$6/MAX(1,N($F19)),0),N($D19)*$G19*$C$6)) -> 0 | R19: =IF(OR($I19="",N($I19)=0,$E19="",$E19="Gratuit"),0,IF($E19="Forfait",N($D19),N($D19)*$I19)) -> 0 | S19: =IF(OR($I19="",N($I19)=0,$E19="",$E19="Gratuit"),0,IF($E19="Forfait",N($D19)*ROUNDUP($C$6/MAX(1,N($F19)),0),N($D19)*$I19*$C$6)) -> 0 | T19: =IF(OR($K19="",N($K19)=0,$E19="",$E19="Gratuit"),0,IF($E19="Forfait",N($D19),N($D19)*$K19)) -> 0 | U19: =IF(OR($K19="",N($K19)=0,$E19="",$E19="Gratuit"),0,IF($E19="Forfait",N($D19)*ROUNDUP($C$6/MAX(1,N($F19)),0),N($D19)*$K19*$C$6)) -> 0
B20: CNB | C20: Offre d'emploi | D20: 0 | E20: Gratuit | G20: 1 | H20: =IF(OR($G20="",N($G20)=0,$E20="",$E20="Gratuit"),0,IF($E20="Forfait",N($D20)/MAX(1,N($F20)),N($D20)*$G20)) -> 0 | I20: 1 | J20: =IF(OR($I20="",N($I20)=0,$E20="",$E20="Gratuit"),0,IF($E20="Forfait",N($D20)/MAX(1,N($F20)),N($D20)*$I20)) -> 0 | K20: 1 | L20: =IF(OR($K20="",N($K20)=0,$E20="",$E20="Gratuit"),0,IF($E20="Forfait",N($D20)/MAX(1,N($F20)),N($D20)*$K20)) -> 0 | M20: Conseil national des barreaux. | O20: =CHOOSE($C$10,G20,I20,K20) -> 1 | P20: =IF(OR($G20="",N($G20)=0,$E20="",$E20="Gratuit"),0,IF($E20="Forfait",N($D20),N($D20)*$G20)) -> 0 | Q20: =IF(OR($G20="",N($G20)=0,$E20="",$E20="Gratuit"),0,IF($E20="Forfait",N($D20)*ROUNDUP($C$6/MAX(1,N($F20)),0),N($D20)*$G20*$C$6)) -> 0 | R20: =IF(OR($I20="",N($I20)=0,$E20="",$E20="Gratuit"),0,IF($E20="Forfait",N($D20),N($D20)*$I20)) -> 0 | S20: =IF(OR($I20="",N($I20)=0,$E20="",$E20="Gratuit"),0,IF($E20="Forfait",N($D20)*ROUNDUP($C$6/MAX(1,N($F20)),0),N($D20)*$I20*$C$6)) -> 0 | T20: =IF(OR($K20="",N($K20)=0,$E20="",$E20="Gratuit"),0,IF($E20="Forfait",N($D20),N($D20)*$K20)) -> 0 | U20: =IF(OR($K20="",N($K20)=0,$E20="",$E20="Gratuit"),0,IF($E20="Forfait",N($D20)*ROUNDUP($C$6/MAX(1,N($F20)),0),N($D20)*$K20*$C$6)) -> 0
B21: Ordre des avocats de Grenoble | C21: Offre d'emploi | D21: 0 | E21: Gratuit | G21: 1 | H21: =IF(OR($G21="",N($G21)=0,$E21="",$E21="Gratuit"),0,IF($E21="Forfait",N($D21)/MAX(1,N($F21)),N($D21)*$G21)) -> 0 | I21: 1 | J21: =IF(OR($I21="",N($I21)=0,$E21="",$E21="Gratuit"),0,IF($E21="Forfait",N($D21)/MAX(1,N($F21)),N($D21)*$I21)) -> 0 | K21: 1 | L21: =IF(OR($K21="",N($K21)=0,$E21="",$E21="Gratuit"),0,IF($E21="Forfait",N($D21)/MAX(1,N($F21)),N($D21)*$K21)) -> 0 | M21: Diffusion auprès du barreau local. | O21: =CHOOSE($C$10,G21,I21,K21) -> 1 | P21: =IF(OR($G21="",N($G21)=0,$E21="",$E21="Gratuit"),0,IF($E21="Forfait",N($D21),N($D21)*$G21)) -> 0 | Q21: =IF(OR($G21="",N($G21)=0,$E21="",$E21="Gratuit"),0,IF($E21="Forfait",N($D21)*ROUNDUP($C$6/MAX(1,N($F21)),0),N($D21)*$G21*$C$6)) -> 0 | R21: =IF(OR($I21="",N($I21)=0,$E21="",$E21="Gratuit"),0,IF($E21="Forfait",N($D21),N($D21)*$I21)) -> 0 | S21: =IF(OR($I21="",N($I21)=0,$E21="",$E21="Gratuit"),0,IF($E21="Forfait",N($D21)*ROUNDUP($C$6/MAX(1,N($F21)),0),N($D21)*$I21*$C$6)) -> 0 | T21: =IF(OR($K21="",N($K21)=0,$E21="",$E21="Gratuit"),0,IF($E21="Forfait",N($D21),N($D21)*$K21)) -> 0 | U21: =IF(OR($K21="",N($K21)=0,$E21="",$E21="Gratuit"),0,IF($E21="Forfait",N($D21)*ROUNDUP($C$6/MAX(1,N($F21)),0),N($D21)*$K21*$C$6)) -> 0
B22: Meta (Facebook, Instagram) | C22: Boost de publication | D22: 10 | E22: Par jour | G22: 0 | H22: =IF(OR($G22="",N($G22)=0,$E22="",$E22="Gratuit"),0,IF($E22="Forfait",N($D22)/MAX(1,N($F22)),N($D22)*$G22)) -> 0 | I22: 10 | J22: =IF(OR($I22="",N($I22)=0,$E22="",$E22="Gratuit"),0,IF($E22="Forfait",N($D22)/MAX(1,N($F22)),N($D22)*$I22)) -> 100 | K22: 30 | L22: =IF(OR($K22="",N($K22)=0,$E22="",$E22="Gratuit"),0,IF($E22="Forfait",N($D22)/MAX(1,N($F22)),N($D22)*$K22)) -> 300 | M22: Budget journalier maximal : la dépense réelle peut être inférieure. | O22: =CHOOSE($C$10,G22,I22,K22) -> 10 | P22: =IF(OR($G22="",N($G22)=0,$E22="",$E22="Gratuit"),0,IF($E22="Forfait",N($D22),N($D22)*$G22)) -> 0 | Q22: =IF(OR($G22="",N($G22)=0,$E22="",$E22="Gratuit"),0,IF($E22="Forfait",N($D22)*ROUNDUP($C$6/MAX(1,N($F22)),0),N($D22)*$G22*$C$6)) -> 0 | R22: =IF(OR($I22="",N($I22)=0,$E22="",$E22="Gratuit"),0,IF($E22="Forfait",N($D22),N($D22)*$I22)) -> 100 | S22: =IF(OR($I22="",N($I22)=0,$E22="",$E22="Gratuit"),0,IF($E22="Forfait",N($D22)*ROUNDUP($C$6/MAX(1,N($F22)),0),N($D22)*$I22*$C$6)) -> 200 | T22: =IF(OR($K22="",N($K22)=0,$E22="",$E22="Gratuit"),0,IF($E22="Forfait",N($D22),N($D22)*$K22)) -> 300 | U22: =IF(OR($K22="",N($K22)=0,$E22="",$E22="Gratuit"),0,IF($E22="Forfait",N($D22)*ROUNDUP($C$6/MAX(1,N($F22)),0),N($D22)*$K22*$C$6)) -> 600
B23: Autre plateforme | H23: =IF(OR($G23="",N($G23)=0,$E23="",$E23="Gratuit"),0,IF($E23="Forfait",N($D23)/MAX(1,N($F23)),N($D23)*$G23)) -> 0 | J23: =IF(OR($I23="",N($I23)=0,$E23="",$E23="Gratuit"),0,IF($E23="Forfait",N($D23)/MAX(1,N($F23)),N($D23)*$I23)) -> 0 | L23: =IF(OR($K23="",N($K23)=0,$E23="",$E23="Gratuit"),0,IF($E23="Forfait",N($D23)/MAX(1,N($F23)),N($D23)*$K23)) -> 0 | M23: Ligne libre. | O23: =CHOOSE($C$10,G23,I23,K23) -> 0 | P23: =IF(OR($G23="",N($G23)=0,$E23="",$E23="Gratuit"),0,IF($E23="Forfait",N($D23),N($D23)*$G23)) -> 0 | Q23: =IF(OR($G23="",N($G23)=0,$E23="",$E23="Gratuit"),0,IF($E23="Forfait",N($D23)*ROUNDUP($C$6/MAX(1,N($F23)),0),N($D23)*$G23*$C$6)) -> 0 | R23: =IF(OR($I23="",N($I23)=0,$E23="",$E23="Gratuit"),0,IF($E23="Forfait",N($D23),N($D23)*$I23)) -> 0 | S23: =IF(OR($I23="",N($I23)=0,$E23="",$E23="Gratuit"),0,IF($E23="Forfait",N($D23)*ROUNDUP($C$6/MAX(1,N($F23)),0),N($D23)*$I23*$C$6)) -> 0 | T23: =IF(OR($K23="",N($K23)=0,$E23="",$E23="Gratuit"),0,IF($E23="Forfait",N($D23),N($D23)*$K23)) -> 0 | U23: =IF(OR($K23="",N($K23)=0,$E23="",$E23="Gratuit"),0,IF($E23="Forfait",N($D23)*ROUNDUP($C$6/MAX(1,N($F23)),0),N($D23)*$K23*$C$6)) -> 0
B24: Autre plateforme | H24: =IF(OR($G24="",N($G24)=0,$E24="",$E24="Gratuit"),0,IF($E24="Forfait",N($D24)/MAX(1,N($F24)),N($D24)*$G24)) -> 0 | J24: =IF(OR($I24="",N($I24)=0,$E24="",$E24="Gratuit"),0,IF($E24="Forfait",N($D24)/MAX(1,N($F24)),N($D24)*$I24)) -> 0 | L24: =IF(OR($K24="",N($K24)=0,$E24="",$E24="Gratuit"),0,IF($E24="Forfait",N($D24)/MAX(1,N($F24)),N($D24)*$K24)) -> 0 | M24: Ligne libre. | O24: =CHOOSE($C$10,G24,I24,K24) -> 0 | P24: =IF(OR($G24="",N($G24)=0,$E24="",$E24="Gratuit"),0,IF($E24="Forfait",N($D24),N($D24)*$G24)) -> 0 | Q24: =IF(OR($G24="",N($G24)=0,$E24="",$E24="Gratuit"),0,IF($E24="Forfait",N($D24)*ROUNDUP($C$6/MAX(1,N($F24)),0),N($D24)*$G24*$C$6)) -> 0 | R24: =IF(OR($I24="",N($I24)=0,$E24="",$E24="Gratuit"),0,IF($E24="Forfait",N($D24),N($D24)*$I24)) -> 0 | S24: =IF(OR($I24="",N($I24)=0,$E24="",$E24="Gratuit"),0,IF($E24="Forfait",N($D24)*ROUNDUP($C$6/MAX(1,N($F24)),0),N($D24)*$I24*$C$6)) -> 0 | T24: =IF(OR($K24="",N($K24)=0,$E24="",$E24="Gratuit"),0,IF($E24="Forfait",N($D24),N($D24)*$K24)) -> 0 | U24: =IF(OR($K24="",N($K24)=0,$E24="",$E24="Gratuit"),0,IF($E24="Forfait",N($D24)*ROUNDUP($C$6/MAX(1,N($F24)),0),N($D24)*$K24*$C$6)) -> 0
B25: Total mensuel (forfait lissé sur sa durée) | G25: =COUNTIFS(G13:G24,">0",$E13:$E24,"<>Gratuit") -> 1 | H25: =SUM(H13:H24) -> 145 | I25: =COUNTIFS(I13:I24,">0",$E13:$E24,"<>Gratuit") -> 4 | J25: =SUM(J13:J24) -> 595 | K25: =COUNTIFS(K13:K24,">0",$E13:$E24,"<>Gratuit") -> 4 | L25: =SUM(L13:L24) -> 1145 | P25: =SUM(P13:P24) -> 290 | Q25: =SUM(Q13:Q24) -> 290 | R25: =SUM(R13:R24) -> 740 | S25: =SUM(S13:S24) -> 1190 | T25: =SUM(T13:T24) -> 1290 | U25: =SUM(U13:U24) -> 2290
B27: SYNTHÈSE DES SCÉNARIOS
B28: Scénario | C28: Contenu | D28: Mensuel moyen | E28: 1er mois | F28: Total campagne | G28: Total TTC | H28: Plateformes payantes
B29: Essentiel | C29: Plateformes gratuites + Village de la Justice | D29: =$Q$25/$C$6 -> 145 | E29: =$P$25 -> 290 | F29: =$Q$25 -> 290 | G29: =IF($C$7="HT",F29*(1+$C$8),F29) -> 348 | H29: =$G$25 -> 1
B30: Équilibré | C30: Essentiel + boosts LinkedIn (15 j) et Meta (10 j) + Indeed 2 semaines par mois | D30: =$S$25/$C$6 -> 595 | E30: =$R$25 -> 740 | F30: =$S$25 -> 1190 | G30: =IF($C$7="HT",F30*(1+$C$8),F30) -> 1428 | H30: =$I$25 -> 4
B31: Intensif | C31: Essentiel + boosts LinkedIn et Meta tous les jours + Indeed chaque semaine | D31: =$U$25/$C$6 -> 1145 | E31: =$T$25 -> 1290 | F31: =$U$25 -> 2290 | G31: =IF($C$7="HT",F31*(1+$C$8),F31) -> 2748 | H31: =$K$25 -> 4
B32: Montants exprimés selon la base choisie dans « Tarifs saisis en » (HT ou TTC). Mensuel moyen = total de la campagne ÷ durée.
B34: HYPOTHÈSES ET MODE D'EMPLOI
B35: • Tarifs communiqués par le cabinet (septembre 2026). Vérifiez s'ils sont HT ou TTC et ajustez « Tarifs saisis en ».
B36: • Village de la Justice : forfait de 290 € pour 2 mois, payé à la publication. Il est renouvelé si la campagne dure plus de 2 mois.
B37: • Boosts LinkedIn et Meta : 10 € par jour correspondent à un budget maximal ; la dépense réelle peut être inférieure. Saisissez le nombre de jours de boost prévus chaque mois.
B38: • Indeed : 100 € par semaine sponsorisée ; saisissez le nombre de semaines par mois (4 au maximum pour un mois plein).
B39: • Plateformes gratuites : quantité 1 = diffusion prévue, 0 = pas de diffusion. Elles n'entrent pas dans le budget mais dans le décompte des plateformes utilisées.
B40: • Pour tester une autre hypothèse, modifiez les quantités d'un scénario ; pour ajouter un support, utilisez les lignes « Autre plateforme ».

Sheet Échéancier
B1: Échéancier mensuel des dépenses
B2: ="Scénario "&Budget!$C$9&" · campagne de "&Budget!$C$6&" mois à partir de "&TEXT(MONTH(Budget!$C$5),"00")&"/"&YEAR(Budget!$C$5) -> Scénario Équilibré · campagne de 2 mois à partir de 10/2026
B3: Décaissements prévus par mois (forfaits payés au début de leur période). Aucune saisie dans cet onglet.
B5: DÉPENSES PAR PLATEFORME ET PAR MOIS
B6: Mois de campagne | C6: 1 | D6: 2 | E6: 3 | F6: 4 | G6: 5 | H6: 6 | I6: 7 | J6: 8 | K6: 9 | L6: 10 | M6: 11 | N6: 12
B7: Plateforme | C7: =EDATE(Budget!$C$5,0) -> 46296 | D7: =EDATE(Budget!$C$5,1) -> 46327 | E7: =EDATE(Budget!$C$5,2) -> 46357 | F7: =EDATE(Budget!$C$5,3) -> 46388 | G7: =EDATE(Budget!$C$5,4) -> 46419 | H7: =EDATE(Budget!$C$5,5) -> 46447 | I7: =EDATE(Budget!$C$5,6) -> 46478 | J7: =EDATE(Budget!$C$5,7) -> 46508 | K7: =EDATE(Budget!$C$5,8) -> 46539 | L7: =EDATE(Budget!$C$5,9) -> 46569 | M7: =EDATE(Budget!$C$5,10) -> 46600 | N7: =EDATE(Budget!$C$5,11) -> 46631 | O7: Total
B8: =IF(Budget!$B$13="","",Budget!$B$13&IF(Budget!$C$13="",""," – "&Budget!$C$13)) -> Village de la Justice – Annonce Premium | C8: =IF(OR(C$6>Budget!$C$6,N(Budget!$O$13)=0,Budget!$E$13="",Budget!$E$13="Gratuit"),0,IF(Budget!$E$13="Forfait",IF(MOD(C$6-1,MAX(1,N(Budget!$F$13)))=0,N(Budget!$D$13),0),N(Budget!$D$13)*Budget!$O$13)) -> 290 | D8: =IF(OR(D$6>Budget!$C$6,N(Budget!$O$13)=0,Budget!$E$13="",Budget!$E$13="Gratuit"),0,IF(Budget!$E$13="Forfait",IF(MOD(D$6-1,MAX(1,N(Budget!$F$13)))=0,N(Budget!$D$13),0),N(Budget!$D$13)*Budget!$O$13)) -> 0 | E8: =IF(OR(E$6>Budget!$C$6,N(Budget!$O$13)=0,Budget!$E$13="",Budget!$E$13="Gratuit"),0,IF(Budget!$E$13="Forfait",IF(MOD(E$6-1,MAX(1,N(Budget!$F$13)))=0,N(Budget!$D$13),0),N(Budget!$D$13)*Budget!$O$13)) -> 0 | F8: =IF(OR(F$6>Budget!$C$6,N(Budget!$O$13)=0,Budget!$E$13="",Budget!$E$13="Gratuit"),0,IF(Budget!$E$13="Forfait",IF(MOD(F$6-1,MAX(1,N(Budget!$F$13)))=0,N(Budget!$D$13),0),N(Budget!$D$13)*Budget!$O$13)) -> 0 | G8: =IF(OR(G$6>Budget!$C$6,N(Budget!$O$13)=0,Budget!$E$13="",Budget!$E$13="Gratuit"),0,IF(Budget!$E$13="Forfait",IF(MOD(G$6-1,MAX(1,N(Budget!$F$13)))=0,N(Budget!$D$13),0),N(Budget!$D$13)*Budget!$O$13)) -> 0 | H8: =IF(OR(H$6>Budget!$C$6,N(Budget!$O$13)=0,Budget!$E$13="",Budget!$E$13="Gratuit"),0,IF(Budget!$E$13="Forfait",IF(MOD(H$6-1,MAX(1,N(Budget!$F$13)))=0,N(Budget!$D$13),0),N(Budget!$D$13)*Budget!$O$13)) -> 0 | I8: =IF(OR(I$6>Budget!$C$6,N(Budget!$O$13)=0,Budget!$E$13="",Budget!$E$13="Gratuit"),0,IF(Budget!$E$13="Forfait",IF(MOD(I$6-1,MAX(1,N(Budget!$F$13)))=0,N(Budget!$D$13),0),N(Budget!$D$13)*Budget!$O$13)) -> 0 | J8: =IF(OR(J$6>Budget!$C$6,N(Budget!$O$13)=0,Budget!$E$13="",Budget!$E$13="Gratuit"),0,IF(Budget!$E$13="Forfait",IF(MOD(J$6-1,MAX(1,N(Budget!$F$13)))=0,N(Budget!$D$13),0),N(Budget!$D$13)*Budget!$O$13)) -> 0 | ... N8: =IF(OR(N$6>Budget!$C$6,N(Budget!$O$13)=0,Budget!$E$13="",Budget!$E$13="Gratuit"),0,IF(Budget!$E$13="Forfait",IF(MOD(N$6-1,MAX(1,N(Budget!$F$13)))=0,N(Budget!$D$13),0),N(Budget!$D$13)*Budget!$O$13)) -> 0 | O8: =SUM(C8:N8) -> 290
B9: =IF(Budget!$B$14="","",Budget!$B$14&IF(Budget!$C$14="",""," – "&Budget!$C$14)) -> RecrutAvocat – Annonce | C9: =IF(OR(C$6>Budget!$C$6,N(Budget!$O$14)=0,Budget!$E$14="",Budget!$E$14="Gratuit"),0,IF(Budget!$E$14="Forfait",IF(MOD(C$6-1,MAX(1,N(Budget!$F$14)))=0,N(Budget!$D$14),0),N(Budget!$D$14)*Budget!$O$14)) -> 0 | D9: =IF(OR(D$6>Budget!$C$6,N(Budget!$O$14)=0,Budget!$E$14="",Budget!$E$14="Gratuit"),0,IF(Budget!$E$14="Forfait",IF(MOD(D$6-1,MAX(1,N(Budget!$F$14)))=0,N(Budget!$D$14),0),N(Budget!$D$14)*Budget!$O$14)) -> 0 | E9: =IF(OR(E$6>Budget!$C$6,N(Budget!$O$14)=0,Budget!$E$14="",Budget!$E$14="Gratuit"),0,IF(Budget!$E$14="Forfait",IF(MOD(E$6-1,MAX(1,N(Budget!$F$14)))=0,N(Budget!$D$14),0),N(Budget!$D$14)*Budget!$O$14)) -> 0 | F9: =IF(OR(F$6>Budget!$C$6,N(Budget!$O$14)=0,Budget!$E$14="",Budget!$E$14="Gratuit"),0,IF(Budget!$E$14="Forfait",IF(MOD(F$6-1,MAX(1,N(Budget!$F$14)))=0,N(Budget!$D$14),0),N(Budget!$D$14)*Budget!$O$14)) -> 0 | G9: =IF(OR(G$6>Budget!$C$6,N(Budget!$O$14)=0,Budget!$E$14="",Budget!$E$14="Gratuit"),0,IF(Budget!$E$14="Forfait",IF(MOD(G$6-1,MAX(1,N(Budget!$F$14)))=0,N(Budget!$D$14),0),N(Budget!$D$14)*Budget!$O$14)) -> 0 | H9: =IF(OR(H$6>Budget!$C$6,N(Budget!$O$14)=0,Budget!$E$14="",Budget!$E$14="Gratuit"),0,IF(Budget!$E$14="Forfait",IF(MOD(H$6-1,MAX(1,N(Budget!$F$14)))=0,N(Budget!$D$14),0),N(Budget!$D$14)*Budget!$O$14)) -> 0 | I9: =IF(OR(I$6>Budget!$C$6,N(Budget!$O$14)=0,Budget!$E$14="",Budget!$E$14="Gratuit"),0,IF(Budget!$E$14="Forfait",IF(MOD(I$6-1,MAX(1,N(Budget!$F$14)))=0,N(Budget!$D$14),0),N(Budget!$D$14)*Budget!$O$14)) -> 0 | J9: =IF(OR(J$6>Budget!$C$6,N(Budget!$O$14)=0,Budget!$E$14="",Budget!$E$14="Gratuit"),0,IF(Budget!$E$14="Forfait",IF(MOD(J$6-1,MAX(1,N(Budget!$F$14)))=0,N(Budget!$D$14),0),N(Budget!$D$14)*Budget!$O$14)) -> 0 | ... N9: =IF(OR(N$6>Budget!$C$6,N(Budget!$O$14)=0,Budget!$E$14="",Budget!$E$14="Gratuit"),0,IF(Budget!$E$14="Forfait",IF(MOD(N$6-1,MAX(1,N(Budget!$F$14)))=0,N(Budget!$D$14),0),N(Budget!$D$14)*Budget!$O$14)) -> 0 | O9: =SUM(C9:N9) -> 0
B10: =IF(Budget!$B$15="","",Budget!$B$15&IF(Budget!$C$15="",""," – "&Budget!$C$15)) -> LinkedIn – Offre d'emploi | C10: =IF(OR(C$6>Budget!$C$6,N(Budget!$O$15)=0,Budget!$E$15="",Budget!$E$15="Gratuit"),0,IF(Budget!$E$15="Forfait",IF(MOD(C$6-1,MAX(1,N(Budget!$F$15)))=0,N(Budget!$D$15),0),N(Budget!$D$15)*Budget!$O$15)) -> 0 | D10: =IF(OR(D$6>Budget!$C$6,N(Budget!$O$15)=0,Budget!$E$15="",Budget!$E$15="Gratuit"),0,IF(Budget!$E$15="Forfait",IF(MOD(D$6-1,MAX(1,N(Budget!$F$15)))=0,N(Budget!$D$15),0),N(Budget!$D$15)*Budget!$O$15)) -> 0 | E10: =IF(OR(E$6>Budget!$C$6,N(Budget!$O$15)=0,Budget!$E$15="",Budget!$E$15="Gratuit"),0,IF(Budget!$E$15="Forfait",IF(MOD(E$6-1,MAX(1,N(Budget!$F$15)))=0,N(Budget!$D$15),0),N(Budget!$D$15)*Budget!$O$15)) -> 0 | F10: =IF(OR(F$6>Budget!$C$6,N(Budget!$O$15)=0,Budget!$E$15="",Budget!$E$15="Gratuit"),0,IF(Budget!$E$15="Forfait",IF(MOD(F$6-1,MAX(1,N(Budget!$F$15)))=0,N(Budget!$D$15),0),N(Budget!$D$15)*Budget!$O$15)) -> 0 | G10: =IF(OR(G$6>Budget!$C$6,N(Budget!$O$15)=0,Budget!$E$15="",Budget!$E$15="Gratuit"),0,IF(Budget!$E$15="Forfait",IF(MOD(G$6-1,MAX(1,N(Budget!$F$15)))=0,N(Budget!$D$15),0),N(Budget!$D$15)*Budget!$O$15)) -> 0 | H10: =IF(OR(H$6>Budget!$C$6,N(Budget!$O$15)=0,Budget!$E$15="",Budget!$E$15="Gratuit"),0,IF(Budget!$E$15="Forfait",IF(MOD(H$6-1,MAX(1,N(Budget!$F$15)))=0,N(Budget!$D$15),0),N(Budget!$D$15)*Budget!$O$15)) -> 0 | I10: =IF(OR(I$6>Budget!$C$6,N(Budget!$O$15)=0,Budget!$E$15="",Budget!$E$15="Gratuit"),0,IF(Budget!$E$15="Forfait",IF(MOD(I$6-1,MAX(1,N(Budget!$F$15)))=0,N(Budget!$D$15),0),N(Budget!$D$15)*Budget!$O$15)) -> 0 | J10: =IF(OR(J$6>Budget!$C$6,N(Budget!$O$15)=0,Budget!$E$15="",Budget!$E$15="Gratuit"),0,IF(Budget!$E$15="Forfait",IF(MOD(J$6-1,MAX(1,N(Budget!$F$15)))=0,N(Budget!$D$15),0),N(Budget!$D$15)*Budget!$O$15)) -> 0 | ... N10: =IF(OR(N$6>Budget!$C$6,N(Budget!$O$15)=0,Budget!$E$15="",Budget!$E$15="Gratuit"),0,IF(Budget!$E$15="Forfait",IF(MOD(N$6-1,MAX(1,N(Budget!$F$15)))=0,N(Budget!$D$15),0),N(Budget!$D$15)*Budget!$O$15)) -> 0 | O10: =SUM(C10:N10) -> 0
B11: =IF(Budget!$B$16="","",Budget!$B$16&IF(Budget!$C$16="",""," – "&Budget!$C$16)) -> LinkedIn – Boost de l'offre | C11: =IF(OR(C$6>Budget!$C$6,N(Budget!$O$16)=0,Budget!$E$16="",Budget!$E$16="Gratuit"),0,IF(Budget!$E$16="Forfait",IF(MOD(C$6-1,MAX(1,N(Budget!$F$16)))=0,N(Budget!$D$16),0),N(Budget!$D$16)*Budget!$O$16)) -> 150 | D11: =IF(OR(D$6>Budget!$C$6,N(Budget!$O$16)=0,Budget!$E$16="",Budget!$E$16="Gratuit"),0,IF(Budget!$E$16="Forfait",IF(MOD(D$6-1,MAX(1,N(Budget!$F$16)))=0,N(Budget!$D$16),0),N(Budget!$D$16)*Budget!$O$16)) -> 150 | E11: =IF(OR(E$6>Budget!$C$6,N(Budget!$O$16)=0,Budget!$E$16="",Budget!$E$16="Gratuit"),0,IF(Budget!$E$16="Forfait",IF(MOD(E$6-1,MAX(1,N(Budget!$F$16)))=0,N(Budget!$D$16),0),N(Budget!$D$16)*Budget!$O$16)) -> 0 | F11: =IF(OR(F$6>Budget!$C$6,N(Budget!$O$16)=0,Budget!$E$16="",Budget!$E$16="Gratuit"),0,IF(Budget!$E$16="Forfait",IF(MOD(F$6-1,MAX(1,N(Budget!$F$16)))=0,N(Budget!$D$16),0),N(Budget!$D$16)*Budget!$O$16)) -> 0 | G11: =IF(OR(G$6>Budget!$C$6,N(Budget!$O$16)=0,Budget!$E$16="",Budget!$E$16="Gratuit"),0,IF(Budget!$E$16="Forfait",IF(MOD(G$6-1,MAX(1,N(Budget!$F$16)))=0,N(Budget!$D$16),0),N(Budget!$D$16)*Budget!$O$16)) -> 0 | H11: =IF(OR(H$6>Budget!$C$6,N(Budget!$O$16)=0,Budget!$E$16="",Budget!$E$16="Gratuit"),0,IF(Budget!$E$16="Forfait",IF(MOD(H$6-1,MAX(1,N(Budget!$F$16)))=0,N(Budget!$D$16),0),N(Budget!$D$16)*Budget!$O$16)) -> 0 | I11: =IF(OR(I$6>Budget!$C$6,N(Budget!$O$16)=0,Budget!$E$16="",Budget!$E$16="Gratuit"),0,IF(Budget!$E$16="Forfait",IF(MOD(I$6-1,MAX(1,N(Budget!$F$16)))=0,N(Budget!$D$16),0),N(Budget!$D$16)*Budget!$O$16)) -> 0 | J11: =IF(OR(J$6>Budget!$C$6,N(Budget!$O$16)=0,Budget!$E$16="",Budget!$E$16="Gratuit"),0,IF(Budget!$E$16="Forfait",IF(MOD(J$6-1,MAX(1,N(Budget!$F$16)))=0,N(Budget!$D$16),0),N(Budget!$D$16)*Budget!$O$16)) -> 0 | ... N11: =IF(OR(N$6>Budget!$C$6,N(Budget!$O$16)=0,Budget!$E$16="",Budget!$E$16="Gratuit"),0,IF(Budget!$E$16="Forfait",IF(MOD(N$6-1,MAX(1,N(Budget!$F$16)))=0,N(Budget!$D$16),0),N(Budget!$D$16)*Budget!$O$16)) -> 0 | O11: =SUM(C11:N11) -> 300
B12: =IF(Budget!$B$17="","",Budget!$B$17&IF(Budget!$C$17="",""," – "&Budget!$C$17)) -> Indeed – Annonce sponsorisée | C12: =IF(OR(C$6>Budget!$C$6,N(Budget!$O$17)=0,Budget!$E$17="",Budget!$E$17="Gratuit"),0,IF(Budget!$E$17="Forfait",IF(MOD(C$6-1,MAX(1,N(Budget!$F$17)))=0,N(Budget!$D$17),0),N(Budget!$D$17)*Budget!$O$17)) -> 200 | D12: =IF(OR(D$6>Budget!$C$6,N(Budget!$O$17)=0,Budget!$E$17="",Budget!$E$17="Gratuit"),0,IF(Budget!$E$17="Forfait",IF(MOD(D$6-1,MAX(1,N(Budget!$F$17)))=0,N(Budget!$D$17),0),N(Budget!$D$17)*Budget!$O$17)) -> 200 | E12: =IF(OR(E$6>Budget!$C$6,N(Budget!$O$17)=0,Budget!$E$17="",Budget!$E$17="Gratuit"),0,IF(Budget!$E$17="Forfait",IF(MOD(E$6-1,MAX(1,N(Budget!$F$17)))=0,N(Budget!$D$17),0),N(Budget!$D$17)*Budget!$O$17)) -> 0 | F12: =IF(OR(F$6>Budget!$C$6,N(Budget!$O$17)=0,Budget!$E$17="",Budget!$E$17="Gratuit"),0,IF(Budget!$E$17="Forfait",IF(MOD(F$6-1,MAX(1,N(Budget!$F$17)))=0,N(Budget!$D$17),0),N(Budget!$D$17)*Budget!$O$17)) -> 0 | G12: =IF(OR(G$6>Budget!$C$6,N(Budget!$O$17)=0,Budget!$E$17="",Budget!$E$17="Gratuit"),0,IF(Budget!$E$17="Forfait",IF(MOD(G$6-1,MAX(1,N(Budget!$F$17)))=0,N(Budget!$D$17),0),N(Budget!$D$17)*Budget!$O$17)) -> 0 | H12: =IF(OR(H$6>Budget!$C$6,N(Budget!$O$17)=0,Budget!$E$17="",Budget!$E$17="Gratuit"),0,IF(Budget!$E$17="Forfait",IF(MOD(H$6-1,MAX(1,N(Budget!$F$17)))=0,N(Budget!$D$17),0),N(Budget!$D$17)*Budget!$O$17)) -> 0 | I12: =IF(OR(I$6>Budget!$C$6,N(Budget!$O$17)=0,Budget!$E$17="",Budget!$E$17="Gratuit"),0,IF(Budget!$E$17="Forfait",IF(MOD(I$6-1,MAX(1,N(Budget!$F$17)))=0,N(Budget!$D$17),0),N(Budget!$D$17)*Budget!$O$17)) -> 0 | J12: =IF(OR(J$6>Budget!$C$6,N(Budget!$O$17)=0,Budget!$E$17="",Budget!$E$17="Gratuit"),0,IF(Budget!$E$17="Forfait",IF(MOD(J$6-1,MAX(1,N(Budget!$F$17)))=0,N(Budget!$D$17),0),N(Budget!$D$17)*Budget!$O$17)) -> 0 | ... N12: =IF(OR(N$6>Budget!$C$6,N(Budget!$O$17)=0,Budget!$E$17="",Budget!$E$17="Gratuit"),0,IF(Budget!$E$17="Forfait",IF(MOD(N$6-1,MAX(1,N(Budget!$F$17)))=0,N(Budget!$D$17),0),N(Budget!$D$17)*Budget!$O$17)) -> 0 | O12: =SUM(C12:N12) -> 400
B13: =IF(Budget!$B$18="","",Budget!$B$18&IF(Budget!$C$18="",""," – "&Budget!$C$18)) -> France Travail – Offre d'emploi | C13: =IF(OR(C$6>Budget!$C$6,N(Budget!$O$18)=0,Budget!$E$18="",Budget!$E$18="Gratuit"),0,IF(Budget!$E$18="Forfait",IF(MOD(C$6-1,MAX(1,N(Budget!$F$18)))=0,N(Budget!$D$18),0),N(Budget!$D$18)*Budget!$O$18)) -> 0 | D13: =IF(OR(D$6>Budget!$C$6,N(Budget!$O$18)=0,Budget!$E$18="",Budget!$E$18="Gratuit"),0,IF(Budget!$E$18="Forfait",IF(MOD(D$6-1,MAX(1,N(Budget!$F$18)))=0,N(Budget!$D$18),0),N(Budget!$D$18)*Budget!$O$18)) -> 0 | E13: =IF(OR(E$6>Budget!$C$6,N(Budget!$O$18)=0,Budget!$E$18="",Budget!$E$18="Gratuit"),0,IF(Budget!$E$18="Forfait",IF(MOD(E$6-1,MAX(1,N(Budget!$F$18)))=0,N(Budget!$D$18),0),N(Budget!$D$18)*Budget!$O$18)) -> 0 | F13: =IF(OR(F$6>Budget!$C$6,N(Budget!$O$18)=0,Budget!$E$18="",Budget!$E$18="Gratuit"),0,IF(Budget!$E$18="Forfait",IF(MOD(F$6-1,MAX(1,N(Budget!$F$18)))=0,N(Budget!$D$18),0),N(Budget!$D$18)*Budget!$O$18)) -> 0 | G13: =IF(OR(G$6>Budget!$C$6,N(Budget!$O$18)=0,Budget!$E$18="",Budget!$E$18="Gratuit"),0,IF(Budget!$E$18="Forfait",IF(MOD(G$6-1,MAX(1,N(Budget!$F$18)))=0,N(Budget!$D$18),0),N(Budget!$D$18)*Budget!$O$18)) -> 0 | H13: =IF(OR(H$6>Budget!$C$6,N(Budget!$O$18)=0,Budget!$E$18="",Budget!$E$18="Gratuit"),0,IF(Budget!$E$18="Forfait",IF(MOD(H$6-1,MAX(1,N(Budget!$F$18)))=0,N(Budget!$D$18),0),N(Budget!$D$18)*Budget!$O$18)) -> 0 | I13: =IF(OR(I$6>Budget!$C$6,N(Budget!$O$18)=0,Budget!$E$18="",Budget!$E$18="Gratuit"),0,IF(Budget!$E$18="Forfait",IF(MOD(I$6-1,MAX(1,N(Budget!$F$18)))=0,N(Budget!$D$18),0),N(Budget!$D$18)*Budget!$O$18)) -> 0 | J13: =IF(OR(J$6>Budget!$C$6,N(Budget!$O$18)=0,Budget!$E$18="",Budget!$E$18="Gratuit"),0,IF(Budget!$E$18="Forfait",IF(MOD(J$6-1,MAX(1,N(Budget!$F$18)))=0,N(Budget!$D$18),0),N(Budget!$D$18)*Budget!$O$18)) -> 0 | ... N13: =IF(OR(N$6>Budget!$C$6,N(Budget!$O$18)=0,Budget!$E$18="",Budget!$E$18="Gratuit"),0,IF(Budget!$E$18="Forfait",IF(MOD(N$6-1,MAX(1,N(Budget!$F$18)))=0,N(Budget!$D$18),0),N(Budget!$D$18)*Budget!$O$18)) -> 0 | O13: =SUM(C13:N13) -> 0
B14: =IF(Budget!$B$19="","",Budget!$B$19&IF(Budget!$C$19="",""," – "&Budget!$C$19)) -> Apec – Offre cadre | C14: =IF(OR(C$6>Budget!$C$6,N(Budget!$O$19)=0,Budget!$E$19="",Budget!$E$19="Gratuit"),0,IF(Budget!$E$19="Forfait",IF(MOD(C$6-1,MAX(1,N(Budget!$F$19)))=0,N(Budget!$D$19),0),N(Budget!$D$19)*Budget!$O$19)) -> 0 | D14: =IF(OR(D$6>Budget!$C$6,N(Budget!$O$19)=0,Budget!$E$19="",Budget!$E$19="Gratuit"),0,IF(Budget!$E$19="Forfait",IF(MOD(D$6-1,MAX(1,N(Budget!$F$19)))=0,N(Budget!$D$19),0),N(Budget!$D$19)*Budget!$O$19)) -> 0 | E14: =IF(OR(E$6>Budget!$C$6,N(Budget!$O$19)=0,Budget!$E$19="",Budget!$E$19="Gratuit"),0,IF(Budget!$E$19="Forfait",IF(MOD(E$6-1,MAX(1,N(Budget!$F$19)))=0,N(Budget!$D$19),0),N(Budget!$D$19)*Budget!$O$19)) -> 0 | F14: =IF(OR(F$6>Budget!$C$6,N(Budget!$O$19)=0,Budget!$E$19="",Budget!$E$19="Gratuit"),0,IF(Budget!$E$19="Forfait",IF(MOD(F$6-1,MAX(1,N(Budget!$F$19)))=0,N(Budget!$D$19),0),N(Budget!$D$19)*Budget!$O$19)) -> 0 | G14: =IF(OR(G$6>Budget!$C$6,N(Budget!$O$19)=0,Budget!$E$19="",Budget!$E$19="Gratuit"),0,IF(Budget!$E$19="Forfait",IF(MOD(G$6-1,MAX(1,N(Budget!$F$19)))=0,N(Budget!$D$19),0),N(Budget!$D$19)*Budget!$O$19)) -> 0 | H14: =IF(OR(H$6>Budget!$C$6,N(Budget!$O$19)=0,Budget!$E$19="",Budget!$E$19="Gratuit"),0,IF(Budget!$E$19="Forfait",IF(MOD(H$6-1,MAX(1,N(Budget!$F$19)))=0,N(Budget!$D$19),0),N(Budget!$D$19)*Budget!$O$19)) -> 0 | I14: =IF(OR(I$6>Budget!$C$6,N(Budget!$O$19)=0,Budget!$E$19="",Budget!$E$19="Gratuit"),0,IF(Budget!$E$19="Forfait",IF(MOD(I$6-1,MAX(1,N(Budget!$F$19)))=0,N(Budget!$D$19),0),N(Budget!$D$19)*Budget!$O$19)) -> 0 | J14: =IF(OR(J$6>Budget!$C$6,N(Budget!$O$19)=0,Budget!$E$19="",Budget!$E$19="Gratuit"),0,IF(Budget!$E$19="Forfait",IF(MOD(J$6-1,MAX(1,N(Budget!$F$19)))=0,N(Budget!$D$19),0),N(Budget!$D$19)*Budget!$O$19)) -> 0 | ... N14: =IF(OR(N$6>Budget!$C$6,N(Budget!$O$19)=0,Budget!$E$19="",Budget!$E$19="Gratuit"),0,IF(Budget!$E$19="Forfait",IF(MOD(N$6-1,MAX(1,N(Budget!$F$19)))=0,N(Budget!$D$19),0),N(Budget!$D$19)*Budget!$O$19)) -> 0 | O14: =SUM(C14:N14) -> 0
B15: =IF(Budget!$B$20="","",Budget!$B$20&IF(Budget!$C$20="",""," – "&Budget!$C$20)) -> CNB – Offre d'emploi | C15: =IF(OR(C$6>Budget!$C$6,N(Budget!$O$20)=0,Budget!$E$20="",Budget!$E$20="Gratuit"),0,IF(Budget!$E$20="Forfait",IF(MOD(C$6-1,MAX(1,N(Budget!$F$20)))=0,N(Budget!$D$20),0),N(Budget!$D$20)*Budget!$O$20)) -> 0 | D15: =IF(OR(D$6>Budget!$C$6,N(Budget!$O$20)=0,Budget!$E$20="",Budget!$E$20="Gratuit"),0,IF(Budget!$E$20="Forfait",IF(MOD(D$6-1,MAX(1,N(Budget!$F$20)))=0,N(Budget!$D$20),0),N(Budget!$D$20)*Budget!$O$20)) -> 0 | E15: =IF(OR(E$6>Budget!$C$6,N(Budget!$O$20)=0,Budget!$E$20="",Budget!$E$20="Gratuit"),0,IF(Budget!$E$20="Forfait",IF(MOD(E$6-1,MAX(1,N(Budget!$F$20)))=0,N(Budget!$D$20),0),N(Budget!$D$20)*Budget!$O$20)) -> 0 | F15: =IF(OR(F$6>Budget!$C$6,N(Budget!$O$20)=0,Budget!$E$20="",Budget!$E$20="Gratuit"),0,IF(Budget!$E$20="Forfait",IF(MOD(F$6-1,MAX(1,N(Budget!$F$20)))=0,N(Budget!$D$20),0),N(Budget!$D$20)*Budget!$O$20)) -> 0 | G15: =IF(OR(G$6>Budget!$C$6,N(Budget!$O$20)=0,Budget!$E$20="",Budget!$E$20="Gratuit"),0,IF(Budget!$E$20="Forfait",IF(MOD(G$6-1,MAX(1,N(Budget!$F$20)))=0,N(Budget!$D$20),0),N(Budget!$D$20)*Budget!$O$20)) -> 0 | H15: =IF(OR(H$6>Budget!$C$6,N(Budget!$O$20)=0,Budget!$E$20="",Budget!$E$20="Gratuit"),0,IF(Budget!$E$20="Forfait",IF(MOD(H$6-1,MAX(1,N(Budget!$F$20)))=0,N(Budget!$D$20),0),N(Budget!$D$20)*Budget!$O$20)) -> 0 | I15: =IF(OR(I$6>Budget!$C$6,N(Budget!$O$20)=0,Budget!$E$20="",Budget!$E$20="Gratuit"),0,IF(Budget!$E$20="Forfait",IF(MOD(I$6-1,MAX(1,N(Budget!$F$20)))=0,N(Budget!$D$20),0),N(Budget!$D$20)*Budget!$O$20)) -> 0 | J15: =IF(OR(J$6>Budget!$C$6,N(Budget!$O$20)=0,Budget!$E$20="",Budget!$E$20="Gratuit"),0,IF(Budget!$E$20="Forfait",IF(MOD(J$6-1,MAX(1,N(Budget!$F$20)))=0,N(Budget!$D$20),0),N(Budget!$D$20)*Budget!$O$20)) -> 0 | ... N15: =IF(OR(N$6>Budget!$C$6,N(Budget!$O$20)=0,Budget!$E$20="",Budget!$E$20="Gratuit"),0,IF(Budget!$E$20="Forfait",IF(MOD(N$6-1,MAX(1,N(Budget!$F$20)))=0,N(Budget!$D$20),0),N(Budget!$D$20)*Budget!$O$20)) -> 0 | O15: =SUM(C15:N15) -> 0
B16: =IF(Budget!$B$21="","",Budget!$B$21&IF(Budget!$C$21="",""," – "&Budget!$C$21)) -> Ordre des avocats de Grenoble – Offre d'emploi | C16: =IF(OR(C$6>Budget!$C$6,N(Budget!$O$21)=0,Budget!$E$21="",Budget!$E$21="Gratuit"),0,IF(Budget!$E$21="Forfait",IF(MOD(C$6-1,MAX(1,N(Budget!$F$21)))=0,N(Budget!$D$21),0),N(Budget!$D$21)*Budget!$O$21)) -> 0 | D16: =IF(OR(D$6>Budget!$C$6,N(Budget!$O$21)=0,Budget!$E$21="",Budget!$E$21="Gratuit"),0,IF(Budget!$E$21="Forfait",IF(MOD(D$6-1,MAX(1,N(Budget!$F$21)))=0,N(Budget!$D$21),0),N(Budget!$D$21)*Budget!$O$21)) -> 0 | E16: =IF(OR(E$6>Budget!$C$6,N(Budget!$O$21)=0,Budget!$E$21="",Budget!$E$21="Gratuit"),0,IF(Budget!$E$21="Forfait",IF(MOD(E$6-1,MAX(1,N(Budget!$F$21)))=0,N(Budget!$D$21),0),N(Budget!$D$21)*Budget!$O$21)) -> 0 | F16: =IF(OR(F$6>Budget!$C$6,N(Budget!$O$21)=0,Budget!$E$21="",Budget!$E$21="Gratuit"),0,IF(Budget!$E$21="Forfait",IF(MOD(F$6-1,MAX(1,N(Budget!$F$21)))=0,N(Budget!$D$21),0),N(Budget!$D$21)*Budget!$O$21)) -> 0 | G16: =IF(OR(G$6>Budget!$C$6,N(Budget!$O$21)=0,Budget!$E$21="",Budget!$E$21="Gratuit"),0,IF(Budget!$E$21="Forfait",IF(MOD(G$6-1,MAX(1,N(Budget!$F$21)))=0,N(Budget!$D$21),0),N(Budget!$D$21)*Budget!$O$21)) -> 0 | H16: =IF(OR(H$6>Budget!$C$6,N(Budget!$O$21)=0,Budget!$E$21="",Budget!$E$21="Gratuit"),0,IF(Budget!$E$21="Forfait",IF(MOD(H$6-1,MAX(1,N(Budget!$F$21)))=0,N(Budget!$D$21),0),N(Budget!$D$21)*Budget!$O$21)) -> 0 | I16: =IF(OR(I$6>Budget!$C$6,N(Budget!$O$21)=0,Budget!$E$21="",Budget!$E$21="Gratuit"),0,IF(Budget!$E$21="Forfait",IF(MOD(I$6-1,MAX(1,N(Budget!$F$21)))=0,N(Budget!$D$21),0),N(Budget!$D$21)*Budget!$O$21)) -> 0 | J16: =IF(OR(J$6>Budget!$C$6,N(Budget!$O$21)=0,Budget!$E$21="",Budget!$E$21="Gratuit"),0,IF(Budget!$E$21="Forfait",IF(MOD(J$6-1,MAX(1,N(Budget!$F$21)))=0,N(Budget!$D$21),0),N(Budget!$D$21)*Budget!$O$21)) -> 0 | ... N16: =IF(OR(N$6>Budget!$C$6,N(Budget!$O$21)=0,Budget!$E$21="",Budget!$E$21="Gratuit"),0,IF(Budget!$E$21="Forfait",IF(MOD(N$6-1,MAX(1,N(Budget!$F$21)))=0,N(Budget!$D$21),0),N(Budget!$D$21)*Budget!$O$21)) -> 0 | O16: =SUM(C16:N16) -> 0
B17: =IF(Budget!$B$22="","",Budget!$B$22&IF(Budget!$C$22="",""," – "&Budget!$C$22)) -> Meta (Facebook, Instagram) – Boost de publication | C17: =IF(OR(C$6>Budget!$C$6,N(Budget!$O$22)=0,Budget!$E$22="",Budget!$E$22="Gratuit"),0,IF(Budget!$E$22="Forfait",IF(MOD(C$6-1,MAX(1,N(Budget!$F$22)))=0,N(Budget!$D$22),0),N(Budget!$D$22)*Budget!$O$22)) -> 100 | D17: =IF(OR(D$6>Budget!$C$6,N(Budget!$O$22)=0,Budget!$E$22="",Budget!$E$22="Gratuit"),0,IF(Budget!$E$22="Forfait",IF(MOD(D$6-1,MAX(1,N(Budget!$F$22)))=0,N(Budget!$D$22),0),N(Budget!$D$22)*Budget!$O$22)) -> 100 | E17: =IF(OR(E$6>Budget!$C$6,N(Budget!$O$22)=0,Budget!$E$22="",Budget!$E$22="Gratuit"),0,IF(Budget!$E$22="Forfait",IF(MOD(E$6-1,MAX(1,N(Budget!$F$22)))=0,N(Budget!$D$22),0),N(Budget!$D$22)*Budget!$O$22)) -> 0 | F17: =IF(OR(F$6>Budget!$C$6,N(Budget!$O$22)=0,Budget!$E$22="",Budget!$E$22="Gratuit"),0,IF(Budget!$E$22="Forfait",IF(MOD(F$6-1,MAX(1,N(Budget!$F$22)))=0,N(Budget!$D$22),0),N(Budget!$D$22)*Budget!$O$22)) -> 0 | G17: =IF(OR(G$6>Budget!$C$6,N(Budget!$O$22)=0,Budget!$E$22="",Budget!$E$22="Gratuit"),0,IF(Budget!$E$22="Forfait",IF(MOD(G$6-1,MAX(1,N(Budget!$F$22)))=0,N(Budget!$D$22),0),N(Budget!$D$22)*Budget!$O$22)) -> 0 | H17: =IF(OR(H$6>Budget!$C$6,N(Budget!$O$22)=0,Budget!$E$22="",Budget!$E$22="Gratuit"),0,IF(Budget!$E$22="Forfait",IF(MOD(H$6-1,MAX(1,N(Budget!$F$22)))=0,N(Budget!$D$22),0),N(Budget!$D$22)*Budget!$O$22)) -> 0 | I17: =IF(OR(I$6>Budget!$C$6,N(Budget!$O$22)=0,Budget!$E$22="",Budget!$E$22="Gratuit"),0,IF(Budget!$E$22="Forfait",IF(MOD(I$6-1,MAX(1,N(Budget!$F$22)))=0,N(Budget!$D$22),0),N(Budget!$D$22)*Budget!$O$22)) -> 0 | J17: =IF(OR(J$6>Budget!$C$6,N(Budget!$O$22)=0,Budget!$E$22="",Budget!$E$22="Gratuit"),0,IF(Budget!$E$22="Forfait",IF(MOD(J$6-1,MAX(1,N(Budget!$F$22)))=0,N(Budget!$D$22),0),N(Budget!$D$22)*Budget!$O$22)) -> 0 | ... N17: =IF(OR(N$6>Budget!$C$6,N(Budget!$O$22)=0,Budget!$E$22="",Budget!$E$22="Gratuit"),0,IF(Budget!$E$22="Forfait",IF(MOD(N$6-1,MAX(1,N(Budget!$F$22)))=0,N(Budget!$D$22),0),N(Budget!$D$22)*Budget!$O$22)) -> 0 | O17: =SUM(C17:N17) -> 200
B18: =IF(Budget!$B$23="","",Budget!$B$23&IF(Budget!$C$23="",""," – "&Budget!$C$23)) -> Autre plateforme | C18: =IF(OR(C$6>Budget!$C$6,N(Budget!$O$23)=0,Budget!$E$23="",Budget!$E$23="Gratuit"),0,IF(Budget!$E$23="Forfait",IF(MOD(C$6-1,MAX(1,N(Budget!$F$23)))=0,N(Budget!$D$23),0),N(Budget!$D$23)*Budget!$O$23)) -> 0 | D18: =IF(OR(D$6>Budget!$C$6,N(Budget!$O$23)=0,Budget!$E$23="",Budget!$E$23="Gratuit"),0,IF(Budget!$E$23="Forfait",IF(MOD(D$6-1,MAX(1,N(Budget!$F$23)))=0,N(Budget!$D$23),0),N(Budget!$D$23)*Budget!$O$23)) -> 0 | E18: =IF(OR(E$6>Budget!$C$6,N(Budget!$O$23)=0,Budget!$E$23="",Budget!$E$23="Gratuit"),0,IF(Budget!$E$23="Forfait",IF(MOD(E$6-1,MAX(1,N(Budget!$F$23)))=0,N(Budget!$D$23),0),N(Budget!$D$23)*Budget!$O$23)) -> 0 | F18: =IF(OR(F$6>Budget!$C$6,N(Budget!$O$23)=0,Budget!$E$23="",Budget!$E$23="Gratuit"),0,IF(Budget!$E$23="Forfait",IF(MOD(F$6-1,MAX(1,N(Budget!$F$23)))=0,N(Budget!$D$23),0),N(Budget!$D$23)*Budget!$O$23)) -> 0 | G18: =IF(OR(G$6>Budget!$C$6,N(Budget!$O$23)=0,Budget!$E$23="",Budget!$E$23="Gratuit"),0,IF(Budget!$E$23="Forfait",IF(MOD(G$6-1,MAX(1,N(Budget!$F$23)))=0,N(Budget!$D$23),0),N(Budget!$D$23)*Budget!$O$23)) -> 0 | H18: =IF(OR(H$6>Budget!$C$6,N(Budget!$O$23)=0,Budget!$E$23="",Budget!$E$23="Gratuit"),0,IF(Budget!$E$23="Forfait",IF(MOD(H$6-1,MAX(1,N(Budget!$F$23)))=0,N(Budget!$D$23),0),N(Budget!$D$23)*Budget!$O$23)) -> 0 | I18: =IF(OR(I$6>Budget!$C$6,N(Budget!$O$23)=0,Budget!$E$23="",Budget!$E$23="Gratuit"),0,IF(Budget!$E$23="Forfait",IF(MOD(I$6-1,MAX(1,N(Budget!$F$23)))=0,N(Budget!$D$23),0),N(Budget!$D$23)*Budget!$O$23)) -> 0 | J18: =IF(OR(J$6>Budget!$C$6,N(Budget!$O$23)=0,Budget!$E$23="",Budget!$E$23="Gratuit"),0,IF(Budget!$E$23="Forfait",IF(MOD(J$6-1,MAX(1,N(Budget!$F$23)))=0,N(Budget!$D$23),0),N(Budget!$D$23)*Budget!$O$23)) -> 0 | ... N18: =IF(OR(N$6>Budget!$C$6,N(Budget!$O$23)=0,Budget!$E$23="",Budget!$E$23="Gratuit"),0,IF(Budget!$E$23="Forfait",IF(MOD(N$6-1,MAX(1,N(Budget!$F$23)))=0,N(Budget!$D$23),0),N(Budget!$D$23)*Budget!$O$23)) -> 0 | O18: =SUM(C18:N18) -> 0
B19: =IF(Budget!$B$24="","",Budget!$B$24&IF(Budget!$C$24="",""," – "&Budget!$C$24)) -> Autre plateforme | C19: =IF(OR(C$6>Budget!$C$6,N(Budget!$O$24)=0,Budget!$E$24="",Budget!$E$24="Gratuit"),0,IF(Budget!$E$24="Forfait",IF(MOD(C$6-1,MAX(1,N(Budget!$F$24)))=0,N(Budget!$D$24),0),N(Budget!$D$24)*Budget!$O$24)) -> 0 | D19: =IF(OR(D$6>Budget!$C$6,N(Budget!$O$24)=0,Budget!$E$24="",Budget!$E$24="Gratuit"),0,IF(Budget!$E$24="Forfait",IF(MOD(D$6-1,MAX(1,N(Budget!$F$24)))=0,N(Budget!$D$24),0),N(Budget!$D$24)*Budget!$O$24)) -> 0 | E19: =IF(OR(E$6>Budget!$C$6,N(Budget!$O$24)=0,Budget!$E$24="",Budget!$E$24="Gratuit"),0,IF(Budget!$E$24="Forfait",IF(MOD(E$6-1,MAX(1,N(Budget!$F$24)))=0,N(Budget!$D$24),0),N(Budget!$D$24)*Budget!$O$24)) -> 0 | F19: =IF(OR(F$6>Budget!$C$6,N(Budget!$O$24)=0,Budget!$E$24="",Budget!$E$24="Gratuit"),0,IF(Budget!$E$24="Forfait",IF(MOD(F$6-1,MAX(1,N(Budget!$F$24)))=0,N(Budget!$D$24),0),N(Budget!$D$24)*Budget!$O$24)) -> 0 | G19: =IF(OR(G$6>Budget!$C$6,N(Budget!$O$24)=0,Budget!$E$24="",Budget!$E$24="Gratuit"),0,IF(Budget!$E$24="Forfait",IF(MOD(G$6-1,MAX(1,N(Budget!$F$24)))=0,N(Budget!$D$24),0),N(Budget!$D$24)*Budget!$O$24)) -> 0 | H19: =IF(OR(H$6>Budget!$C$6,N(Budget!$O$24)=0,Budget!$E$24="",Budget!$E$24="Gratuit"),0,IF(Budget!$E$24="Forfait",IF(MOD(H$6-1,MAX(1,N(Budget!$F$24)))=0,N(Budget!$D$24),0),N(Budget!$D$24)*Budget!$O$24)) -> 0 | I19: =IF(OR(I$6>Budget!$C$6,N(Budget!$O$24)=0,Budget!$E$24="",Budget!$E$24="Gratuit"),0,IF(Budget!$E$24="Forfait",IF(MOD(I$6-1,MAX(1,N(Budget!$F$24)))=0,N(Budget!$D$24),0),N(Budget!$D$24)*Budget!$O$24)) -> 0 | J19: =IF(OR(J$6>Budget!$C$6,N(Budget!$O$24)=0,Budget!$E$24="",Budget!$E$24="Gratuit"),0,IF(Budget!$E$24="Forfait",IF(MOD(J$6-1,MAX(1,N(Budget!$F$24)))=0,N(Budget!$D$24),0),N(Budget!$D$24)*Budget!$O$24)) -> 0 | ... N19: =IF(OR(N$6>Budget!$C$6,N(Budget!$O$24)=0,Budget!$E$24="",Budget!$E$24="Gratuit"),0,IF(Budget!$E$24="Forfait",IF(MOD(N$6-1,MAX(1,N(Budget!$F$24)))=0,N(Budget!$D$24),0),N(Budget!$D$24)*Budget!$O$24)) -> 0 | O19: =SUM(C19:N19) -> 0
B20: ="Total du mois ("&Budget!$C$7&")" -> Total du mois (HT) | C20: =SUM(C8:C19) -> 740 | D20: =SUM(D8:D19) -> 450 | E20: =SUM(E8:E19) -> 0 | F20: =SUM(F8:F19) -> 0 | G20: =SUM(G8:G19) -> 0 | H20: =SUM(H8:H19) -> 0 | I20: =SUM(I8:I19) -> 0 | J20: =SUM(J8:J19) -> 0 | ... O20: =SUM(O8:O19) -> 1190
B21: =IF(Budget!$C$7="HT","Total du mois TTC","Total du mois HT") -> Total du mois TTC | C21: =IF(Budget!$C$7="HT",C20*(1+Budget!$C$8),C20/(1+Budget!$C$8)) -> 888 | D21: =IF(Budget!$C$7="HT",D20*(1+Budget!$C$8),D20/(1+Budget!$C$8)) -> 540 | E21: =IF(Budget!$C$7="HT",E20*(1+Budget!$C$8),E20/(1+Budget!$C$8)) -> 0 | F21: =IF(Budget!$C$7="HT",F20*(1+Budget!$C$8),F20/(1+Budget!$C$8)) -> 0 | G21: =IF(Budget!$C$7="HT",G20*(1+Budget!$C$8),G20/(1+Budget!$C$8)) -> 0 | H21: =IF(Budget!$C$7="HT",H20*(1+Budget!$C$8),H20/(1+Budget!$C$8)) -> 0 | I21: =IF(Budget!$C$7="HT",I20*(1+Budget!$C$8),I20/(1+Budget!$C$8)) -> 0 | J21: =IF(Budget!$C$7="HT",J20*(1+Budget!$C$8),J20/(1+Budget!$C$8)) -> 0 | ... O21: =IF(Budget!$C$7="HT",O20*(1+Budget!$C$8),O20/(1+Budget!$C$8)) -> 1428
B22: Cumul depuis le début | C22: =SUM($C$20:C20) -> 740 | D22: =SUM($C$20:D20) -> 1190 | E22: =SUM($C$20:E20) -> 1190 | F22: =SUM($C$20:F20) -> 1190 | G22: =SUM($C$20:G20) -> 1190 | H22: =SUM($C$20:H20) -> 1190 | I22: =SUM($C$20:I20) -> 1190 | J22: =SUM($C$20:J20) -> 1190 | ... N22: =SUM($C$20:N20) -> 1190
